Workbook

Sheet Sales_Data
A1: Month | B1: Year | C1: Category | D1: Region | E1: Orders | F1: Revenue | G1: Profit
A2: 2023-01 | B2: 2023 | C2: Electronics | D2: East | E2: 6 | F2: 390775 | G2: 39105
A3: 2023-01 | B3: 2023 | C3: Electronics | D3: North | E3: 9 | F3: 726522 | G3: 44645
A4: 2023-01 | B4: 2023 | C4: Electronics | D4: South | E4: 13 | F4: 529729 | G4: 17376
A5: 2023-01 | B5: 2023 | C5: Electronics | D5: West | E5: 16 | F5: 1082243 | G5: -4720
A6: 2023-01 | B6: 2023 | C6: Fashion | D6: East | E6: 6 | F6: 52341 | G6: 20547
A7: 2023-01 | B7: 2023 | C7: Fashion | D7: North | E7: 13 | F7: 91195 | G7: 39362
A8: 2023-01 | B8: 2023 | C8: Fashion | D8: South | E8: 19 | F8: 96911 | G8: 39618
A9: 2023-01 | B9: 2023 | C9: Fashion | D9: West | E9: 24 | F9: 108292 | G9: 40345
A10: 2023-01 | B10: 2023 | C10: Grocery | D10: East | E10: 10 | F10: 3203 | G10: 359
A11: 2023-01 | B11: 2023 | C11: Grocery | D11: North | E11: 9 | F11: 4030 | G11: 202
A12: 2023-01 | B12: 2023 | C12: Grocery | D12: South | E12: 14 | F12: 7536 | G12: 355
A13: 2023-01 | B13: 2023 | C13: Grocery | D13: West | E13: 17 | F13: 7276 | G13: 377
... A385: 2024-12 | B385: 2024 | C385: Home & Kitchen | D385: West | E385: 65 | F385: 1057251 | G385: 236266

Sheet Summary
A1: E-commerce sales summary (Delivered orders, INR)
A2: All numbers below are live SUMIFS formulas on the Sales_Data sheet.
A4: Revenue by category
A5: Category | B5: Revenue | C5: Profit | D5: Margin % | E5: Share of revenue
A6: Electronics | B6: =SUMIFS(Sales_Data!$F$2:$F$385,Sales_Data!$C$2:$C$385,A6) -> 251253738 | C6: =SUMIFS(Sales_Data!$G$2:$G$385,Sales_Data!$C$2:$C$385,A6) -> 7611422 | D6: =IF(B6=0,0,C6/B6) -> 0.030293766 | E6: =IF(B$10=0,0,B6/B$10) -> 0.75034002
A7: Fashion | B7: =SUMIFS(Sales_Data!$F$2:$F$385,Sales_Data!$C$2:$C$385,A7) -> 22371313 | C7: =SUMIFS(Sales_Data!$G$2:$G$385,Sales_Data!$C$2:$C$385,A7) -> 8990703 | D7: =IF(B7=0,0,C7/B7) -> 0.40188535 | E7: =IF(B$10=0,0,B7/B$10) -> 0.06680932
A8: Grocery | B8: =SUMIFS(Sales_Data!$F$2:$F$385,Sales_Data!$C$2:$C$385,A8) -> 1737699 | C8: =SUMIFS(Sales_Data!$G$2:$G$385,Sales_Data!$C$2:$C$385,A8) -> 154993 | D8: =IF(B8=0,0,C8/B8) -> 0.089194389 | E8: =IF(B$10=0,0,B8/B$10) -> 0.0051894356
A9: Home & Kitchen | B9: =SUMIFS(Sales_Data!$F$2:$F$385,Sales_Data!$C$2:$C$385,A9) -> 59490426 | C9: =SUMIFS(Sales_Data!$G$2:$G$385,Sales_Data!$C$2:$C$385,A9) -> 13371192 | D9: =IF(B9=0,0,C9/B9) -> 0.22476208 | E9: =IF(B$10=0,0,B9/B$10) -> 0.17766123
A10: Total | B10: =SUM(B6:B9) -> 334853176 | C10: =SUM(C6:C9) -> 30128310 | D10: =IF(B10=0,0,C10/B10) -> 0.089974688 | E10: =SUM(E6:E9) -> 1
A13: Revenue by region
A14: Region | B14: Revenue | C14: Profit | D14: Margin % | E14: Share of revenue
A15: East | B15: =SUMIFS(Sales_Data!$F$2:$F$385,Sales_Data!$D$2:$D$385,A15) -> 47959262 | C15: =SUMIFS(Sales_Data!$G$2:$G$385,Sales_Data!$D$2:$D$385,A15) -> 4122093 | D15: =IF(B15=0,0,C15/B15) -> 0.085949884 | E15: =IF(B$19=0,0,B15/B$19) -> 0.14322475
A16: North | B16: =SUMIFS(Sales_Data!$F$2:$F$385,Sales_Data!$D$2:$D$385,A16) -> 67001896 | C16: =SUMIFS(Sales_Data!$G$2:$G$385,Sales_Data!$D$2:$D$385,A16) -> 5744423 | D16: =IF(B16=0,0,C16/B16) -> 0.085735231 | E16: =IF(B$19=0,0,B16/B$19) -> 0.20009336
A17: South | B17: =SUMIFS(Sales_Data!$F$2:$F$385,Sales_Data!$D$2:$D$385,A17) -> 119727543 | C17: =SUMIFS(Sales_Data!$G$2:$G$385,Sales_Data!$D$2:$D$385,A17) -> 11128350 | D17: =IF(B17=0,0,C17/B17) -> 0.092947284 | E17: =IF(B$19=0,0,B17/B$19) -> 0.35755236
A18: West | B18: =SUMIFS(Sales_Data!$F$2:$F$385,Sales_Data!$D$2:$D$385,A18) -> 100164475 | C18: =SUMIFS(Sales_Data!$G$2:$G$385,Sales_Data!$D$2:$D$385,A18) -> 9133444 | D18: =IF(B18=0,0,C18/B18) -> 0.091184464 | E18: =IF(B$19=0,0,B18/B$19) -> 0.29912954
A19: Total | B19: =SUM(B15:B18) -> 334853176 | C19: =SUM(C15:C18) -> 30128310 | D19: =IF(B19=0,0,C19/B19) -> 0.089974688 | E19: =SUM(E15:E18) -> 1
A21: Revenue by year
A22: Year | B22: Revenue | C22: Profit | D22: Margin % | E22: Share of revenue
A23: 2023 | B23: =SUMIFS(Sales_Data!$F$2:$F$385,Sales_Data!$B$2:$B$385,A23) -> 127157084 | C23: =SUMIFS(Sales_Data!$G$2:$G$385,Sales_Data!$B$2:$B$385,A23) -> 12060016 | D23: =IF(B23=0,0,C23/B23) -> 0.094843446 | E23: =IF(B$25=0,0,B23/B$25) -> 0.37973982
A24: 2024 | B24: =SUMIFS(Sales_Data!$F$2:$F$385,Sales_Data!$B$2:$B$385,A24) -> 207696092 | C24: =SUMIFS(Sales_Data!$G$2:$G$385,Sales_Data!$B$2:$B$385,A24) -> 18068294 | D24: =IF(B24=0,0,C24/B24) -> 0.086993905 | E24: =IF(B$25=0,0,B24/B$25) -> 0.62026018
A25: Total | B25: =SUM(B23:B24) -> 334853176 | C25: =SUM(C23:C24) -> 30128310 | D25: =IF(B25=0,0,C25/B25) -> 0.089974688 | E25: =SUM(E23:E24) -> 1

Sheet Pivot_Guide
A1: HOW TO BUILD THE PIVOT TABLE (takes ~2 minutes) - this is the Excel skill to show in interviews
A3: 1. Open the Sales_Data sheet and click any cell inside the table (it is already an Excel Table named SalesTbl).
A4: 2. Insert > PivotTable > New Worksheet.
A5: 3. Rows: Category. Columns: Year. Values: Sum of Revenue and Sum of Profit.
A6: 4. Add a calculated field: Margin = Profit / Revenue (PivotTable Analyze > Fields, Items & Sets > Calculated Field).
A7: 5. Insert > Slicer > Region and Month so stakeholders can filter interactively.
A8: 6. Sort the Category rows by Sum of Revenue (largest first) and apply Conditional Formatting > Data Bars.
A9: 7. Insert > PivotChart (clustered column) next to the table and label the axes in INR.
A11: Interview talking point: the Summary sheet cross-checks the PivotTable - both must return identical totals.
